.gitignore
LICENSE.mkd
MANIFEST.in
README.mkd
exceptions.py
requirements.txt
setup.cfg
setup.py
docs/Makefile
docs/conf.py
docs/configuration.rst
docs/index.rst
docs/make.bat
docs/quickstart.rst
docs/_static/theme_override.css
docs/api/alg_classful.rst
docs/api/alg_classless.rst
docs/api/algorithms.rst
docs/api/global.rst
docs/api/index.rst
docs/tutorial/index.rst
docs/tutorial/tutorial_part1.rst
docs/tutorial/tutorial_part2.rst
example/__init__.py
example/config.py
example/run.py
example/rules/__init__.py
example/rules/qos_formulas.py
example/rules/download/__init__.py
example/rules/download/download.py
example/rules/upload/__init__.py
example/rules/upload/upload.py
pyqos/__init__.py
pyqos/app.py
pyqos/config.py
pyqos/decorators.py
pyqos/exceptions.py
pyqos/tools.py
pyqos.egg-info/PKG-INFO
pyqos.egg-info/SOURCES.txt
pyqos.egg-info/dependency_links.txt
pyqos.egg-info/requires.txt
pyqos.egg-info/top_level.txt
pyqos/algorithms/__init__.py
pyqos/algorithms/classless_qdiscs.py
pyqos/algorithms/htb.py
pyqos/backend/__init__.py
pyqos/backend/tc.py
pyqos/tests/backend/test_tc.py