Metadata-Version: 2.1
Name: pyqos
Version: 0.3.0
Summary: Framework that helps setting a QoS on Linux
Home-page: https://github.com/Anthony25/pyqos
Author: Anthony25 <Anthony Ruhier>
Author-email: anthony.ruhier@gmail.com
License: Simplified BSD
Keywords: networking qos linux development
Classifier: Development Status :: 4 - Beta
Classifier: Operating System :: POSIX :: Linux
Classifier: Programming Language :: Python :: 3 :: Only
Classifier: Topic :: System :: Networking
Classifier: License :: OSI Approved :: BSD License
License-File: LICENSE.mkd
